finqual/__init__.py
finqual/cca.py
finqual/core.py
finqual/stocktwit.py
finqual/config/__init__.py
finqual/config/headers.py
finqual/data/gaap_labels.parquet
finqual/data/gaap_labels_v2.parquet
finqual/data/gaap_trees.json
finqual/data/ifrs_labels.parquet
finqual/data/ifrs_trees.json
finqual/data/sector_mapping.parquet
finqual/data/tickers_sectors.parquet
finqual/node_classes/__init__.py
finqual/node_classes/node.py
finqual/node_classes/node_tree.py
finqual/sec_edgar/__init__.py
finqual/sec_edgar/sec_api.py
finqual/sec_edgar/entities/exceptions.py
finqual/sec_edgar/entities/models.py
finqual-4.5.11.dist-info/licenses/LICENSE.md
finqual-4.5.11.dist-info/METADATA
finqual-4.5.11.dist-info/WHEEL
finqual-4.5.11.dist-info/top_level.txt
finqual-4.5.11.dist-info/RECORD
