Metadata-Version: 2.4
Name: finqual
Version: 4.5.11
Summary: A Python package to help investors to conduct financial research, analysis and comparable company analysis.
Home-page: https://github.com/harryy-he/finqual
Author: Harry
Classifier: Programming Language :: Python :: 3
Classifier: License :: OSI Approved :: MIT License
Classifier: Operating System :: OS Independent
Requires-Python: >=3.10
License-File: LICENSE.md
Requires-Dist: pandas>=2.2.3
Requires-Dist: polars>=1.35.1
Requires-Dist: cloudscraper>=1.2.71
Requires-Dist: requests==2.32.4
Requires-Dist: ratelimit>=2.2.1
Requires-Dist: matplotlib>=3.8.0
Requires-Dist: pyarrow>=12.0.0
Requires-Dist: ijson>=3.4.0
Requires-Dist: numpy>=2.2.6
Requires-Dist: pydantic==2.12.4
Dynamic: author
Dynamic: classifier
Dynamic: description
Dynamic: description-content-type
Dynamic: home-page
Dynamic: license-file
Dynamic: requires-dist
Dynamic: requires-python
Dynamic: summary
